Renjian3rdFix1/README.md
Renjian3rdFix1/__init__.py
Renjian3rdFix1/__main__.py
Renjian3rdFix1/file.epub
Renjian3rdFix1/index.html
Renjian3rdFix1/css/__init__.py
Renjian3rdFix1/css/annotations.css
Renjian3rdFix1/css/main.css
Renjian3rdFix1/css/normalize.css
Renjian3rdFix1/css/popup.css
Renjian3rdFix1/font/__init__.py
Renjian3rdFix1/font/fontello.eot
Renjian3rdFix1/font/fontello.svg
Renjian3rdFix1/font/fontello.ttf
Renjian3rdFix1/font/fontello.woff
Renjian3rdFix1/img/__init__.py
Renjian3rdFix1/img/annotator-glyph-sprite.png
Renjian3rdFix1/img/annotator-icon-sprite.png
Renjian3rdFix1/img/apple-touch-icon.png
Renjian3rdFix1/img/cancelfullscreen.png
Renjian3rdFix1/img/close.png
Renjian3rdFix1/img/fullscreen.png
Renjian3rdFix1/img/loader.gif
Renjian3rdFix1/img/menu-icon.png
Renjian3rdFix1/img/save.png
Renjian3rdFix1/img/saved.png
Renjian3rdFix1/img/settings-s.png
Renjian3rdFix1/img/settings.png
Renjian3rdFix1/img/star.png
Renjian3rdFix1/js/__init__.py
Renjian3rdFix1/js/epub.js
Renjian3rdFix1/js/epub.min.js
Renjian3rdFix1/js/epub.min.map
Renjian3rdFix1/js/hooks.min.js
Renjian3rdFix1/js/hooks.min.map
Renjian3rdFix1/js/reader.js
Renjian3rdFix1/js/reader.js.map
Renjian3rdFix1/js/reader.min.js
Renjian3rdFix1/js/reader.min.map
Renjian3rdFix1/js/hooks/__init__.py
Renjian3rdFix1/js/hooks/extensions/__init__.py
Renjian3rdFix1/js/hooks/extensions/highlight.js
Renjian3rdFix1/js/libs/__init__.py
Renjian3rdFix1/js/libs/jquery.min.js
Renjian3rdFix1/js/libs/localforage.min.js
Renjian3rdFix1/js/libs/screenfull.js
Renjian3rdFix1/js/libs/screenfull.min.js
Renjian3rdFix1/js/libs/zip.min.js
Renjian3rdFix1/js/plugins/__init__.py
Renjian3rdFix1/js/plugins/hypothesis.js
Renjian3rdFix1/js/plugins/search.js
renjian_3rd_fix1-2025.3.24.0.dist-info/METADATA
renjian_3rd_fix1-2025.3.24.0.dist-info/WHEEL
renjian_3rd_fix1-2025.3.24.0.dist-info/entry_points.txt
renjian_3rd_fix1-2025.3.24.0.dist-info/top_level.txt
renjian_3rd_fix1-2025.3.24.0.dist-info/RECORD
